{
  "id": "19f8b74d438940d60",
  "mode": "standalone",
  "provider": "codex",
  "provider_session_id": null,
  "attachment": "standalone",
  "worktree": {
    "branch": "refine/standalone/19f8b74d438940d60",
    "path": "/home/buddy/projects/refine-next/.git/refine-standalone-worktrees/19f8b74d438940d60"
  },
  "created_at": "2026-07-22T20:11:57Z",
  "updated_at": "2026-07-22T20:11:57Z",
  "transcript_events": [],
  "importable_artifacts": [],
  "closed": false,
  "interrupted": false,
  "interruption_detail": null
}
